fancy_cli/api.py
fancy_cli/cli.py
fancy_cli/assets/folders/macos.icns
fancy_cli/assets/folders/win10.icns
fancy_cli/assets/folders/win11.icns
fancy_cli/assets/icon_colors/blue.icns
fancy_cli/assets/icon_colors/default.icns
fancy_cli/assets/icon_colors/green.icns
fancy_cli/assets/icon_colors/indigo.icns
fancy_cli/assets/icon_colors/orange.icns
fancy_cli/assets/icon_colors/pink.icns
fancy_cli/assets/icon_colors/red.icns
fancy_cli/assets/icon_colors/violet.icns
fancy_cli/assets/icon_colors/windows.icns
fancy_cli/assets/icon_colors/yellow.icns
fancy_cli-0.1.0.post3.dist-info/METADATA
fancy_cli-0.1.0.post3.dist-info/WHEEL
fancy_cli-0.1.0.post3.dist-info/entry_points.txt
fancy_cli-0.1.0.post3.dist-info/licenses/LICENSE
fancy_cli-0.1.0.post3.dist-info/RECORD
