Metadata-Version: 2.3
Name: fancy-cli
Version: 0.1.0.post3
Summary: Folder Art with Neat Colors for You
Project-URL: Homepage, https://fancy-projects.github.io/cli
Project-URL: Documentation, https://fancy-projects.github.io/cli/docs
Project-URL: Repository, https://github.com/fancy-projects/fancy-cli
Project-URL: Changelog, https://fancy-projects.github.io/changelog
License: MIT License
License-File: LICENSE
Requires-Python: >=3.8
Requires-Dist: numpy>=1.26.4
Requires-Dist: pillow>=10.3.0
Requires-Dist: typer>=0.12.3
